trytond/modules/sale_shipment_tolerance/__init__.py
trytond/modules/sale_shipment_tolerance/configuration.py
trytond/modules/sale_shipment_tolerance/configuration.xml
trytond/modules/sale_shipment_tolerance/exceptions.py
trytond/modules/sale_shipment_tolerance/message.xml
trytond/modules/sale_shipment_tolerance/sale.py
trytond/modules/sale_shipment_tolerance/stock.py
trytond/modules/sale_shipment_tolerance/tryton.cfg
trytond/modules/sale_shipment_tolerance/locale/bg.po
trytond/modules/sale_shipment_tolerance/locale/ca.po
trytond/modules/sale_shipment_tolerance/locale/cs.po
trytond/modules/sale_shipment_tolerance/locale/de.po
trytond/modules/sale_shipment_tolerance/locale/es.po
trytond/modules/sale_shipment_tolerance/locale/es_419.po
trytond/modules/sale_shipment_tolerance/locale/et.po
trytond/modules/sale_shipment_tolerance/locale/fa.po
trytond/modules/sale_shipment_tolerance/locale/fi.po
trytond/modules/sale_shipment_tolerance/locale/fr.po
trytond/modules/sale_shipment_tolerance/locale/hu.po
trytond/modules/sale_shipment_tolerance/locale/id.po
trytond/modules/sale_shipment_tolerance/locale/it.po
trytond/modules/sale_shipment_tolerance/locale/lo.po
trytond/modules/sale_shipment_tolerance/locale/lt.po
trytond/modules/sale_shipment_tolerance/locale/nl.po
trytond/modules/sale_shipment_tolerance/locale/pl.po
trytond/modules/sale_shipment_tolerance/locale/pt.po
trytond/modules/sale_shipment_tolerance/locale/ro.po
trytond/modules/sale_shipment_tolerance/locale/ru.po
trytond/modules/sale_shipment_tolerance/locale/sl.po
trytond/modules/sale_shipment_tolerance/locale/tr.po
trytond/modules/sale_shipment_tolerance/locale/uk.po
trytond/modules/sale_shipment_tolerance/locale/zh_CN.po
trytond/modules/sale_shipment_tolerance/tests/__init__.py
trytond/modules/sale_shipment_tolerance/tests/scenario_sale_over_shipment_tolerance.rst
trytond/modules/sale_shipment_tolerance/tests/scenario_sale_under_shipment_tolerance.rst
trytond/modules/sale_shipment_tolerance/tests/test_module.py
trytond_sale_shipment_tolerance-7.8.0.dist-info/licenses/LICENSE
trytond_sale_shipment_tolerance-7.8.0.dist-info/METADATA
trytond_sale_shipment_tolerance-7.8.0.dist-info/WHEEL
trytond_sale_shipment_tolerance-7.8.0.dist-info/entry_points.txt
trytond_sale_shipment_tolerance-7.8.0.dist-info/top_level.txt
trytond_sale_shipment_tolerance-7.8.0.dist-info/RECORD
